nif/__init__.py
nif/cleaner.py
nif/control.py
nif/exceptions.py
nif/generator.py
nif/identifier.py
nif/validator.py
nif-0.1.0.dist-info/METADATA
nif-0.1.0.dist-info/WHEEL
nif-0.1.0.dist-info/RECORD
